map_pde/__init__.py
map_pde/client.py
map_pde/constant.py
map_pde/util.py
map_pde-0.2.1.dist-info/LICENSE
map_pde-0.2.1.dist-info/METADATA
map_pde-0.2.1.dist-info/WHEEL
map_pde-0.2.1.dist-info/top_level.txt
map_pde-0.2.1.dist-info/RECORD
