Metadata-Version: 2.1
Name: map-pde
Version: 0.2.1
Summary: A package can be used to access waveform data in the map system!
Home-page: https://github.com/Diend-7/pde
Author: WangPeiXian
Author-email: 2825642414@qq.com
License: MIT
License-File: LICENSE
Requires-Dist: obspy
